[
  {
    "trend_arrow": "45_UP", 
    "system_time": "2016-02-17T21:11:07", 
    "display_time": "2016-02-17T13:11:57", 
    "glucose": 133
  }, 
  {
    "trend_arrow": "SINGLE_UP", 
    "system_time": "2016-02-17T21:06:07", 
    "display_time": "2016-02-17T13:06:57", 
    "glucose": 126
  }, 
  {
    "trend_arrow": "45_UP", 
    "system_time": "2016-02-17T21:01:07", 
    "display_time": "2016-02-17T13:01:57", 
    "glucose": 117
  }, 
  {
    "trend_arrow": "FLAT", 
    "system_time": "2016-02-17T20:56:07", 
    "display_time": "2016-02-17T12:56:57", 
    "glucose": 103
  }, 
  {
    "trend_arrow": "FLAT", 
    "system_time": "2016-02-17T20:51:07", 
    "display_time": "2016-02-17T12:51:57", 
    "glucose": 94
  }
]