[
  {
    "trend_arrow": "FLAT", 
    "system_time": "2016-01-28T21:22:29", 
    "display_time": "2016-01-28T13:23:19", 
    "glucose": 259
  }, 
  {
    "trend_arrow": "FLAT", 
    "system_time": "2016-01-28T21:17:29", 
    "display_time": "2016-01-28T13:18:19", 
    "glucose": 252
  }, 
  {
    "trend_arrow": "FLAT", 
    "system_time": "2016-01-28T21:12:29", 
    "display_time": "2016-01-28T13:13:19", 
    "glucose": 247
  }, 
  {
    "trend_arrow": "45_UP", 
    "system_time": "2016-01-28T21:07:29", 
    "display_time": "2016-01-28T13:08:19", 
    "glucose": 247
  }, 
  {
    "trend_arrow": "45_UP", 
    "system_time": "2016-01-28T21:02:29", 
    "display_time": "2016-01-28T13:03:19", 
    "glucose": 245
  }
]