[
  {
    "trend_arrow": "FLAT", 
    "system_time": "2016-02-23T10:40:45", 
    "display_time": "2016-02-23T02:41:35", 
    "glucose": 132
  }, 
  {
    "trend_arrow": "FLAT", 
    "system_time": "2016-02-23T10:35:45", 
    "display_time": "2016-02-23T02:36:35", 
    "glucose": 131
  }, 
  {
    "trend_arrow": "FLAT", 
    "system_time": "2016-02-23T10:30:45", 
    "display_time": "2016-02-23T02:31:35", 
    "glucose": 133
  }, 
  {
    "trend_arrow": "FLAT", 
    "system_time": "2016-02-23T10:25:45", 
    "display_time": "2016-02-23T02:26:35", 
    "glucose": 132
  }, 
  {
    "trend_arrow": "FLAT", 
    "system_time": "2016-02-23T10:20:45", 
    "display_time": "2016-02-23T02:21:35", 
    "glucose": 131
  }
]