[
  {
    "trend_arrow": "45_UP", 
    "system_time": "2016-02-25T16:40:36", 
    "display_time": "2016-02-25T08:41:26", 
    "glucose": 306
  }, 
  {
    "trend_arrow": "45_UP", 
    "system_time": "2016-02-25T16:35:36", 
    "display_time": "2016-02-25T08:36:27", 
    "glucose": 298
  }, 
  {
    "trend_arrow": "SINGLE_UP", 
    "system_time": "2016-02-25T16:30:36", 
    "display_time": "2016-02-25T08:31:27", 
    "glucose": 291
  }, 
  {
    "trend_arrow": "SINGLE_UP", 
    "system_time": "2016-02-25T16:25:36", 
    "display_time": "2016-02-25T08:26:27", 
    "glucose": 282
  }, 
  {
    "trend_arrow": "SINGLE_UP", 
    "system_time": "2016-02-25T16:20:36", 
    "display_time": "2016-02-25T08:21:27", 
    "glucose": 271
  }
]