[
  {
    "trend_arrow": "45_UP", 
    "system_time": "2016-02-24T16:40:40", 
    "display_time": "2016-02-24T08:41:30", 
    "glucose": 212
  }, 
  {
    "trend_arrow": "45_UP", 
    "system_time": "2016-02-24T16:30:40", 
    "display_time": "2016-02-24T08:31:30", 
    "glucose": 194
  }, 
  {
    "trend_arrow": "SINGLE_UP", 
    "system_time": "2016-02-24T16:25:40", 
    "display_time": "2016-02-24T08:26:30", 
    "glucose": 188
  }, 
  {
    "trend_arrow": "SINGLE_UP", 
    "system_time": "2016-02-24T16:20:40", 
    "display_time": "2016-02-24T08:21:31", 
    "glucose": 179
  }, 
  {
    "trend_arrow": "45_UP", 
    "system_time": "2016-02-24T16:15:40", 
    "display_time": "2016-02-24T08:16:30", 
    "glucose": 168
  }
]