[
  {
    "trend_arrow": "FLAT", 
    "system_time": "2016-02-26T14:15:33", 
    "display_time": "2016-02-26T06:16:23", 
    "glucose": 100
  }, 
  {
    "trend_arrow": "FLAT", 
    "system_time": "2016-02-26T14:10:33", 
    "display_time": "2016-02-26T06:11:23", 
    "glucose": 95
  }, 
  {
    "trend_arrow": "FLAT", 
    "system_time": "2016-02-26T14:05:33", 
    "display_time": "2016-02-26T06:06:23", 
    "glucose": 89
  }, 
  {
    "trend_arrow": "FLAT", 
    "system_time": "2016-02-26T14:00:33", 
    "display_time": "2016-02-26T06:01:23", 
    "glucose": 91
  }, 
  {
    "trend_arrow": "FLAT", 
    "system_time": "2016-02-26T13:55:33", 
    "display_time": "2016-02-26T05:56:23", 
    "glucose": 87
  }
]